congress_gov_api_client/__init__.py
congress_gov_api_client/api/__init__.py
congress_gov_api_client/api/amendments/__init__.py
congress_gov_api_client/api/amendments/amendment.py
congress_gov_api_client/api/amendments/amendmentactions.py
congress_gov_api_client/api/amendments/amendmentamendments.py
congress_gov_api_client/api/amendments/amendmentcongress.py
congress_gov_api_client/api/amendments/amendmentcosponsors.py
congress_gov_api_client/api/amendments/amendmentdetails.py
congress_gov_api_client/api/amendments/amendmentlist.py
congress_gov_api_client/api/amendments/amendments_text.py
congress_gov_api_client/api/bill/__init__.py
congress_gov_api_client/api/bill/bill_actions.py
congress_gov_api_client/api/bill/bill_amendments.py
congress_gov_api_client/api/bill/bill_committees.py
congress_gov_api_client/api/bill/bill_cosponsors.py
congress_gov_api_client/api/bill/bill_details.py
congress_gov_api_client/api/bill/bill_list_all.py
congress_gov_api_client/api/bill/bill_list_by_congress.py
congress_gov_api_client/api/bill/bill_list_by_type.py
congress_gov_api_client/api/bill/bill_relatedbills.py
congress_gov_api_client/api/bill/bill_subjects.py
congress_gov_api_client/api/bill/bill_summaries.py
congress_gov_api_client/api/bill/bill_text.py
congress_gov_api_client/api/bill/bill_titles.py
congress_gov_api_client/api/bill/law_list_by_congress.py
congress_gov_api_client/api/bill/law_list_by_congress_and_law_type.py
congress_gov_api_client/api/bill/law_list_by_congress_law_type_and_law_number.py
congress_gov_api_client/api/bound_congressional_record/__init__.py
congress_gov_api_client/api/bound_congressional_record/bound_congressional_record_list.py
congress_gov_api_client/api/bound_congressional_record/bound_congressional_record_list_by_year.py
congress_gov_api_client/api/bound_congressional_record/bound_congressional_record_list_by_year_and_month.py
congress_gov_api_client/api/bound_congressional_record/bound_congressional_record_list_by_year_and_month_and_day.py
congress_gov_api_client-3.0.5.dist-info/METADATA
congress_gov_api_client-3.0.5.dist-info/WHEEL
congress_gov_api_client-3.0.5.dist-info/RECORD
